      {
        "minlatlng": { "lat": 42.67411388345063, "lng": -7.414044979959726}, "maxlatlng": { "lat": 42.82721424587071, "lng": -7.241524877026677},
        "name": "Triacastela - Sarria",
          "geo": [
            {
              "lat": "42.755853133276105",
              "lng": "-7.241524877026677",
              "ele": "677.38623046875"
            },
            {
              "lat": "42.755770487710834",
              "lng": "-7.241627806797624",
              "ele": "662.8125"
            },
            {
              "lat": "42.755731176584959",
              "lng": "-7.241897955536842",
              "ele": "661.84375"
            },
            {
              "lat": "42.755542499944568",
              "lng": "-7.242385279387236",
              "ele": "660.3671875"
            },
            {
              "lat": "42.755096079781651",
              "lng": "-7.243561176583171",
              "ele": "657.87890625"
            },
            {
              "lat": "42.754850825294852",
              "lng": "-7.24347610026598",
              "ele": "654.40234375"
            },
            {
              "lat": "42.754460899159312",
              "lng": "-7.243514740839601",
              "ele": "652.875"
            },
            {
              "lat": "42.754045911133289",
              "lng": "-7.244272883981466",
              "ele": "657.96484375"
            },
            {
              "lat": "42.753695379942656",
              "lng": "-7.244180766865611",
              "ele": "657.31640625"
            },
            {
              "lat": "42.752865320071578",
              "lng": "-7.24408789537847",
              "ele": "660.93359375"
            },
            {
              "lat": "42.752658203244209",
              "lng": "-7.244149670004845",
              "ele": "662.19921875"
            },
            {
              "lat": "42.752544963732362",
              "lng": "-7.244373969733715",
              "ele": "664.3515625"
            },
            {
              "lat": "42.752500958740711",
              "lng": "-7.24462928250432",
              "ele": "663.85546875"
            },
            {
              "lat": "42.752532390877604",
              "lng": "-7.24504703655839",
              "ele": "667.3359375"
            },
            {
              "lat": "42.75241294875741",
              "lng": "-7.245828397572041",
              "ele": "671.171875"
            },
            {
              "lat": "42.752375230193138",
              "lng": "-7.246238356456161",
              "ele": "675.65625"
            },
            {
              "lat": "42.75241294875741",
              "lng": "-7.246632892638445",
              "ele": "672.62890625"
            },
            {
              "lat": "42.752570193260908",
              "lng": "-7.246942352503538",
              "ele": "672.84375"
            },
            {
              "lat": "42.752884598448873",
              "lng": "-7.247445182874799",
              "ele": "672.734375"
            },
            {
              "lat": "42.753148628398776",
              "lng": "-7.247901661321521",
              "ele": "670.671875"
            },
            {
              "lat": "42.753406455740333",
              "lng": "-7.24845863878727",
              "ele": "670.49609375"
            },
            {
              "lat": "42.75370828807354",
              "lng": "-7.24941928870976",
              "ele": "673.578125"
            },
            {
              "lat": "42.753846673294902",
              "lng": "-7.250471385195851",
              "ele": "672.265625"
            },
            {
              "lat": "42.753928396850824",
              "lng": "-7.251090221107006",
              "ele": "675.2109375"
            },
            {
              "lat": "42.75399754755199",
              "lng": "-7.251802012324333",
              "ele": "674.3125"
            },
            {
              "lat": "42.753494549542665",
              "lng": "-7.252977825701237",
              "ele": "671.6181640625"
            },
            {
              "lat": "42.753243343904614",
              "lng": "-7.253426341339946",
              "ele": "666.98046875"
            },
            {
              "lat": "42.752972943708301",
              "lng": "-7.253851806744933",
              "ele": "672.9375"
            },
            {
              "lat": "42.75283464230597",
              "lng": "-7.253960100933909",
              "ele": "671.96484375"
            },
            {
              "lat": "42.752419570460916",
              "lng": "-7.254130253568292",
              "ele": "661.4140625"
            },
            {
              "lat": "42.752149254083633",
              "lng": "-7.25446293130517",
              "ele": "661.4609375"
            },
            {
              "lat": "42.751639885827899",
              "lng": "-7.255352586507797",
              "ele": "653.2734375"
            },
            {
              "lat": "42.751319194212556",
              "lng": "-7.256118441000581",
              "ele": "648.13671875"
            },
            {
              "lat": "42.751281475648284",
              "lng": "-7.256435612216592",
              "ele": "657.198486328125"
            },
            {
              "lat": "42.751205954700708",
              "lng": "-7.256636610254645",
              "ele": "645.37109375"
            },
            {
              "lat": "42.751249959692359",
              "lng": "-7.257147151976824",
              "ele": "642.03125"
            },
            {
              "lat": "42.751702750101686",
              "lng": "-7.2585937846452",
              "ele": "638.046875"
            },
            {
              "lat": "42.751753041520715",
              "lng": "-7.258864520117641",
              "ele": "637.37890625"
            },
            {
              "lat": "42.751753041520715",
              "lng": "-7.259406074881554",
              "ele": "635.94921875"
            },
            {
              "lat": "42.751646088436246",
              "lng": "-7.259963052347302",
              "ele": "634.83203125"
            },
            {
              "lat": "42.751507787033916",
              "lng": "-7.260373095050454",
              "ele": "632.36328125"
            },
            {
              "lat": "42.751363115385175",
              "lng": "-7.26062061265111",
              "ele": "631.19921875"
            },
            {
              "lat": "42.751168236136436",
              "lng": "-7.260922361165285",
              "ele": "638.452880859375"
            },
            {
              "lat": "42.750986181199551",
              "lng": "-7.261014981195331",
              "ele": "631.1796875"
            },
            {
              "lat": "42.750627771019936",
              "lng": "-7.261479170992971",
              "ele": "624.8203125"
            },
            {
              "lat": "42.750219069421291",
              "lng": "-7.262631850317121",
              "ele": "621.58203125"
            },
            {
              "lat": "42.750080684199929",
              "lng": "-7.263157898560166",
              "ele": "619.74609375"
            },
            {
              "lat": "42.749923523515463",
              "lng": "-7.263560146093369",
              "ele": "627.878173828125"
            },
            {
              "lat": "42.749326648190618",
              "lng": "-7.264449717476964",
              "ele": "623.41796875"
            },
            {
              "lat": "42.748169610276818",
              "lng": "-7.265408942475915",
              "ele": "621.171875"
            },
            {
              "lat": "42.747842632234097",
              "lng": "-7.265594685450196",
              "ele": "618.69140625"
            },
            {
              "lat": "42.745836926624179",
              "lng": "-7.267729640007019",
              "ele": "617.3037109375"
            },
            {
              "lat": "42.745939856395125",
              "lng": "-7.26912128739059",
              "ele": "616.58203125"
            },
            {
              "lat": "42.745726034045219",
              "lng": "-7.270475132390857",
              "ele": "610.574462890625"
            },
            {
              "lat": "42.744965208694339",
              "lng": "-7.270939238369465",
              "ele": "611.265625"
            },
            {
              "lat": "42.744063818827271",
              "lng": "-7.271411893889308",
              "ele": "616.34228515625"
            },
            {
              "lat": "42.743808338418603",
              "lng": "-7.272084122523665",
              "ele": "613.83984375"
            },
            {
              "lat": "42.743783192709088",
              "lng": "-7.272455440834165",
              "ele": "612.08984375"
            },
            {
              "lat": "42.743663750588894",
              "lng": "-7.272617882117629",
              "ele": "613.46484375"
            },
            {
              "lat": "42.743437187746167",
              "lng": "-7.272695330902934",
              "ele": "613.93896484375"
            },
            {
              "lat": "42.741537680849433",
              "lng": "-7.273315172642469",
              "ele": "596.635498046875"
            },
            {
              "lat": "42.740941224619746",
              "lng": "-7.273066816851497",
              "ele": "591.125"
            },
            {
              "lat": "42.740695970132947",
              "lng": "-7.272896664217114",
              "ele": "590.47265625"
            },
            {
              "lat": "42.740463372319937",
              "lng": "-7.272834805771709",
              "ele": "590"
            },
            {
              "lat": "42.740311240777373",
              "lng": "-7.272919295355678",
              "ele": "592.3095703125"
            },
            {
              "lat": "42.740211831405759",
              "lng": "-7.273391783237457",
              "ele": "590.867431640625"
            },
            {
              "lat": "42.740312414243817",
              "lng": "-7.27365480735898",
              "ele": "597.00390625"
            },
            {
              "lat": "42.740375278517604",
              "lng": "-7.274227291345596",
              "ele": "599"
            },
            {
              "lat": "42.740501090884209",
              "lng": "-7.274846127256751",
              "ele": "601.9609375"
            },
            {
              "lat": "42.740450799465179",
              "lng": "-7.275093728676438",
              "ele": "597.39453125"
            },
            {
              "lat": "42.740444513037801",
              "lng": "-7.275287099182606",
              "ele": "596.59375"
            },
            {
              "lat": "42.74063310585916",
              "lng": "-7.275789929553866",
              "ele": "606.34375"
            },
            {
              "lat": "42.74072740226984",
              "lng": "-7.27614582516253",
              "ele": "603.49609375"
            },
            {
              "lat": "42.74078406393528",
              "lng": "-7.276656366884708",
              "ele": "603.8984375"
            },
            {
              "lat": "42.740997802466154",
              "lng": "-7.277157520875335",
              "ele": "605.859375"
            },
            {
              "lat": "42.741148760542274",
              "lng": "-7.277466980740428",
              "ele": "607.5703125"
            },
            {
              "lat": "42.741123614832759",
              "lng": "-7.278054971247912",
              "ele": "601.0546875"
            },
            {
              "lat": "42.741245068609715",
              "lng": "-7.280247258022428",
              "ele": "602.8837890625"
            },
            {
              "lat": "42.742643924430013",
              "lng": "-7.28546884842217",
              "ele": "595.674072265625"
            },
            {
              "lat": "42.742517441511154",
              "lng": "-7.286187428981066",
              "ele": "588.609375"
            },
            {
              "lat": "42.74227486923337",
              "lng": "-7.287325691431761",
              "ele": "588.15625"
            },
            {
              "lat": "42.74197781458497",
              "lng": "-7.288326658308506",
              "ele": "577.4091796875"
            },
            {
              "lat": "42.741502309218049",
              "lng": "-7.288696048781276",
              "ele": "576.3671875"
            },
            {
              "lat": "42.741178935393691",
              "lng": "-7.288850778713822",
              "ele": "577.171875"
            },
            {
              "lat": "42.740981290116906",
              "lng": "-7.288895035162568",
              "ele": "580.5859375"
            },
            {
              "lat": "42.740855561569333",
              "lng": "-7.289049681276083",
              "ele": "583.3828125"
            },
            {
              "lat": "42.740847263485193",
              "lng": "-7.289486294612289",
              "ele": "584.11328125"
            },
            {
              "lat": "42.740734023973346",
              "lng": "-7.289681928232312",
              "ele": "587.8984375"
            },
            {
              "lat": "42.74044836871326",
              "lng": "-7.290172604843974",
              "ele": "595.1484375"
            },
            {
              "lat": "42.740367483347654",
              "lng": "-7.290600333362818",
              "ele": "596.82421875"
            },
            {
              "lat": "42.740262458100915",
              "lng": "-7.290835697203875",
              "ele": "597.1171875"
            },
            {
              "lat": "42.740106135606766",
              "lng": "-7.290875511243939",
              "ele": "598.59765625"
            },
            {
              "lat": "42.739847637712955",
              "lng": "-7.290776772424579",
              "ele": "600.34375"
            },
            {
              "lat": "42.739664409309626",
              "lng": "-7.290717093273997",
              "ele": "601.94921875"
            },
            {
              "lat": "42.739515965804458",
              "lng": "-7.291582021862268",
              "ele": "598.557861328125"
            },
            {
              "lat": "42.739508086815476",
              "lng": "-7.291645389050245",
              "ele": "601.30078125"
            },
            {
              "lat": "42.739597018808126",
              "lng": "-7.291847644373775",
              "ele": "593.80859375"
            },
            {
              "lat": "42.739632055163383",
              "lng": "-7.291947137564421",
              "ele": "590.17578125"
            },
            {
              "lat": "42.739626690745354",
              "lng": "-7.292096335440874",
              "ele": "587.87890625"
            },
            {
              "lat": "42.739443378522992",
              "lng": "-7.292653312906623",
              "ele": "581.765625"
            },
            {
              "lat": "42.739351764321327",
              "lng": "-7.293034605681896",
              "ele": "577.4091796875"
            },
            {
              "lat": "42.739432314410806",
              "lng": "-7.293100906535983",
              "ele": "571.99609375"
            },
            {
              "lat": "42.739561647176743",
              "lng": "-7.293269969522953",
              "ele": "570.83203125"
            },
            {
              "lat": "42.739631719887257",
              "lng": "-7.293369462713599",
              "ele": "570.55859375"
            },
            {
              "lat": "42.739779911935329",
              "lng": "-7.293485468253493",
              "ele": "570.54296875"
            },
            {
              "lat": "42.739930870011449",
              "lng": "-7.293578339740634",
              "ele": "572.7578125"
            },
            {
              "lat": "42.740014437586069",
              "lng": "-7.293638018891215",
              "ele": "574.46875"
            },
            {
              "lat": "42.740014437586069",
              "lng": "-7.293684454634786",
              "ele": "574.93359375"
            },
            {
              "lat": "42.740267738699913",
              "lng": "-7.294503366574645",
              "ele": "579.86328125"
            },
            {
              "lat": "42.740335129201412",
              "lng": "-7.294622724875808",
              "ele": "580.1953125"
            },
            {
              "lat": "42.740553896874189",
              "lng": "-7.295610699802637",
              "ele": "583.29296875"
            },
            {
              "lat": "42.740509891882539",
              "lng": "-7.295881435275078",
              "ele": "582.215576171875"
            },
            {
              "lat": "42.740440741181374",
              "lng": "-7.296639578416944",
              "ele": "580.29296875"
            },
            {
              "lat": "42.739476654678583",
              "lng": "-7.298357281833887",
              "ele": "576.44775390625"
            },
            {
              "lat": "42.7396484836936",
              "lng": "-7.299138307571411",
              "ele": "574.4375"
            },
            {
              "lat": "42.739749066531658",
              "lng": "-7.299617920070887",
              "ele": "576.8046875"
            },
            {
              "lat": "42.739730207249522",
              "lng": "-7.300182692706585",
              "ele": "571.19921875"
            },
            {
              "lat": "42.739900024607778",
              "lng": "-7.300832541659474",
              "ele": "574.04443359375"
            },
            {
              "lat": "42.740151230245829",
              "lng": "-7.301250379532576",
              "ele": "572.5390625"
            },
            {
              "lat": "42.741660559549928",
              "lng": "-7.303106719627976",
              "ele": "594.232177734375"
            },
            {
              "lat": "42.741817384958267",
              "lng": "-7.303880536928773",
              "ele": "594.328125"
            },
            {
              "lat": "42.741880249232054",
              "lng": "-7.305009998381138",
              "ele": "591.77734375"
            },
            {
              "lat": "42.74184881709516",
              "lng": "-7.30565213598311",
              "ele": "594.712646484375"
            },
            {
              "lat": "42.741936827078462",
              "lng": "-7.305814577266574",
              "ele": "589.1640625"
            },
            {
              "lat": "42.742314096540213",
              "lng": "-7.306131748482585",
              "ele": "586.8125"
            },
            {
              "lat": "42.742496486753225",
              "lng": "-7.306247754022479",
              "ele": "588.203125"
            },
            {
              "lat": "42.742628501728177",
              "lng": "-7.306417990475893",
              "ele": "587.30078125"
            },
            {
              "lat": "42.742653731256723",
              "lng": "-7.306541791185737",
              "ele": "588.945068359375"
            },
            {
              "lat": "42.742559434846044",
              "lng": "-7.306650001555681",
              "ele": "585.83984375"
            },
            {
              "lat": "42.742314180359244",
              "lng": "-7.306804731488228",
              "ele": "582.64453125"
            },
            {
              "lat": "42.74228903464973",
              "lng": "-7.306990390643477",
              "ele": "584.53515625"
            },
            {
              "lat": "42.742213597521186",
              "lng": "-7.307237992063165",
              "ele": "583.48828125"
            },
            {
              "lat": "42.742421133443713",
              "lng": "-7.307887757197022",
              "ele": "582.390625"
            },
            {
              "lat": "42.742427419871092",
              "lng": "-7.308034775778651",
              "ele": "580.546875"
            },
            {
              "lat": "42.742307893931866",
              "lng": "-7.308367369696498",
              "ele": "571.59375"
            },
            {
              "lat": "42.74219473823905",
              "lng": "-7.308413805440068",
              "ele": "569.40625"
            },
            {
              "lat": "42.741987202316523",
              "lng": "-7.30831322260201",
              "ele": "566.29296875"
            },
            {
              "lat": "42.742081582546234",
              "lng": "-7.308583958074451",
              "ele": "567.75390625"
            },
            {
              "lat": "42.741880333051085",
              "lng": "-7.309411754831672",
              "ele": "563.69140625"
            },
            {
              "lat": "42.741918051615357",
              "lng": "-7.310092533007264",
              "ele": "571.9140625"
            },
            {
              "lat": "42.74152192287147",
              "lng": "-7.310827458277345",
              "ele": "584.13818359375"
            },
            {
              "lat": "42.741270968690515",
              "lng": "-7.311051674187183",
              "ele": "575.8984375"
            },
            {
              "lat": "42.740642074495554",
              "lng": "-7.311461716890335",
              "ele": "580.10546875"
            },
            {
              "lat": "42.740151649340987",
              "lng": "-7.311446210369468",
              "ele": "582.9453125"
            },
            {
              "lat": "42.74003840982914",
              "lng": "-7.311407569795847",
              "ele": "584.618896484375"
            },
            {
              "lat": "42.739950735121965",
              "lng": "-7.311887182295322",
              "ele": "583.796875"
            },
            {
              "lat": "42.739950735121965",
              "lng": "-7.312506102025509",
              "ele": "586.44140625"
            },
            {
              "lat": "42.739862725138664",
              "lng": "-7.312970208004117",
              "ele": "583.01953125"
            },
            {
              "lat": "42.7395483199507",
              "lng": "-7.313751569017768",
              "ele": "583.46484375"
            },
            {
              "lat": "42.739196196198463",
              "lng": "-7.314130682498217",
              "ele": "576.15625"
            },
            {
              "lat": "42.739076670259237",
              "lng": "-7.314347270876169",
              "ele": "588.46435546875"
            },
            {
              "lat": "42.739007519558072",
              "lng": "-7.314370488747954",
              "ele": "578.370361328125"
            },
            {
              "lat": "42.737966403365135",
              "lng": "-7.314114673063159",
              "ele": "557.7021484375"
            },
            {
              "lat": "42.737372629344463",
              "lng": "-7.314687659963965",
              "ele": "565.392578125"
            },
            {
              "lat": "42.737812763080001",
              "lng": "-7.315995069220662",
              "ele": "564.911865234375"
            },
            {
              "lat": "42.737623583525419",
              "lng": "-7.31632724404335",
              "ele": "561.29296875"
            },
            {
              "lat": "42.737178923562169",
              "lng": "-7.316299667581916",
              "ele": "568.93359375"
            },
            {
              "lat": "42.737098122015595",
              "lng": "-7.316437801346183",
              "ele": "568.765625"
            },
            {
              "lat": "42.736891508102417",
              "lng": "-7.316642235964537",
              "ele": "572.6025390625"
            },
            {
              "lat": "42.736289603635669",
              "lng": "-7.316388096660376",
              "ele": "586.060791015625"
            },
            {
              "lat": "42.736397562548518",
              "lng": "-7.317062085494399",
              "ele": "589.90625"
            },
            {
              "lat": "42.736118948087096",
              "lng": "-7.318222559988499",
              "ele": "592.3203125"
            },
            {
              "lat": "42.735490137711167",
              "lng": "-7.31978083960712",
              "ele": "605.97265625"
            },
            {
              "lat": "42.735413610935211",
              "lng": "-7.319891564548016",
              "ele": "603.0625"
            },
            {
              "lat": "42.735274555161595",
              "lng": "-7.320410739630461",
              "ele": "612.49609375"
            },
            {
              "lat": "42.735023014247417",
              "lng": "-7.321173325181007",
              "ele": "614.900390625"
            },
            {
              "lat": "42.734569301828742",
              "lng": "-7.321764919906855",
              "ele": "611.609375"
            },
            {
              "lat": "42.734326729550958",
              "lng": "-7.322085360065103",
              "ele": "606.515625"
            },
            {
              "lat": "42.733823396265507",
              "lng": "-7.322532953694463",
              "ele": "598.557861328125"
            },
            {
              "lat": "42.733468590304255",
              "lng": "-7.322627082467079",
              "ele": "592.40234375"
            },
            {
              "lat": "42.733149658888578",
              "lng": "-7.322654658928514",
              "ele": "589.69140625"
            },
            {
              "lat": "42.732700472697616",
              "lng": "-7.322616018354893",
              "ele": "585.580078125"
            },
            {
              "lat": "42.732148272916675",
              "lng": "-7.323273830115795",
              "ele": "579.85546875"
            },
            {
              "lat": "42.731847362592816",
              "lng": "-7.323649590834975",
              "ele": "578.29296875"
            },
            {
              "lat": "42.731178067624569",
              "lng": "-7.324191145598888",
              "ele": "574.04443359375"
            },
            {
              "lat": "42.730998443439603",
              "lng": "-7.324251914396882",
              "ele": "570.26953125"
            },
            {
              "lat": "42.730877157300711",
              "lng": "-7.324279490858316",
              "ele": "568.0234375"
            },
            {
              "lat": "42.730737933889031",
              "lng": "-7.32421319000423",
              "ele": "563.6640625"
            },
            {
              "lat": "42.73045496083796",
              "lng": "-7.323682783171535",
              "ele": "558.182861328125"
            },
            {
              "lat": "42.730374075472355",
              "lng": "-7.323798788711429",
              "ele": "550.5625"
            },
            {
              "lat": "42.730374075472355",
              "lng": "-7.324340343475342",
              "ele": "549.07421875"
            },
            {
              "lat": "42.73036066442728",
              "lng": "-7.324887346476317",
              "ele": "542.6015625"
            },
            {
              "lat": "42.730508856475353",
              "lng": "-7.325329408049583",
              "ele": "538.96875"
            },
            {
              "lat": "42.730684038251638",
              "lng": "-7.325533842667937",
              "ele": "538.4609375"
            },
            {
              "lat": "42.730764839798212",
              "lng": "-7.325683040544391",
              "ele": "535.591552734375"
            },
            {
              "lat": "42.730962485074997",
              "lng": "-7.325594695284963",
              "ele": "535.1109619140625"
            },
            {
              "lat": "42.731312848627567",
              "lng": "-7.325495202094317",
              "ele": "539.51171875"
            },
            {
              "lat": "42.731869826093316",
              "lng": "-7.325086249038577",
              "ele": "535.6015625"
            },
            {
              "lat": "42.732071913778782",
              "lng": "-7.324942583218217",
              "ele": "534.1328125"
            },
            {
              "lat": "42.732188673689961",
              "lng": "-7.32503654435277",
              "ele": "532.707763671875"
            },
            {
              "lat": "42.732568960636854",
              "lng": "-7.32561070472002",
              "ele": "530.24609375"
            },
            {
              "lat": "42.732694689184427",
              "lng": "-7.32569913379848",
              "ele": "534.66015625"
            },
            {
              "lat": "42.732797954231501",
              "lng": "-7.325958888977766",
              "ele": "533.6689453125"
            },
            {
              "lat": "42.732640793547034",
              "lng": "-7.326318053528667",
              "ele": "586.060791015625"
            },
            {
              "lat": "42.732488075271249",
              "lng": "-7.326533803716302",
              "ele": "542.9921875"
            },
            {
              "lat": "42.73232638835907",
              "lng": "-7.326716193929315",
              "ele": "544.3671875"
            },
            {
              "lat": "42.732155732810497",
              "lng": "-7.326821135357022",
              "ele": "542.50390625"
            },
            {
              "lat": "42.731872759759426",
              "lng": "-7.326926160603762",
              "ele": "542.0859375"
            },
            {
              "lat": "42.731521725654602",
              "lng": "-7.326925657689571",
              "ele": "532.22705078125"
            },
            {
              "lat": "42.731171948835254",
              "lng": "-7.326887603849173",
              "ele": "540.578125"
            },
            {
              "lat": "42.730821585282683",
              "lng": "-7.326782662421465",
              "ele": "536.875"
            },
            {
              "lat": "42.730511706322432",
              "lng": "-7.326561631634831",
              "ele": "524.0557861328125"
            },
            {
              "lat": "42.730287155136466",
              "lng": "-7.326545035466552",
              "ele": "531.33203125"
            },
            {
              "lat": "42.729977192357183",
              "lng": "-7.326616868376732",
              "ele": "530.2109375"
            },
            {
              "lat": "42.729743672534823",
              "lng": "-7.32679364271462",
              "ele": "530.23828125"
            },
            {
              "lat": "42.729478636756539",
              "lng": "-7.327147359028459",
              "ele": "530.62109375"
            },
            {
              "lat": "42.729182168841362",
              "lng": "-7.32790432870388",
              "ele": "535.96484375"
            },
            {
              "lat": "42.729051914066076",
              "lng": "-7.328468011692166",
              "ele": "534.29296875"
            },
            {
              "lat": "42.729034395888448",
              "lng": "-7.32869734056294",
              "ele": "524.5364990234375"
            },
            {
              "lat": "42.729006903246045",
              "lng": "-7.329089194536209",
              "ele": "531.578125"
            },
            {
              "lat": "42.729159621521831",
              "lng": "-7.329597556963563",
              "ele": "534.79296875"
            },
            {
              "lat": "42.729545859619975",
              "lng": "-7.330310354009271",
              "ele": "534.77734375"
            },
            {
              "lat": "42.730408273637295",
              "lng": "-7.331813396885991",
              "ele": "535.8359375"
            },
            {
              "lat": "42.730592424049973",
              "lng": "-7.332249926403165",
              "ele": "538.1015625"
            },
            {
              "lat": "42.730686720460653",
              "lng": "-7.332658795639873",
              "ele": "538.4453125"
            },
            {
              "lat": "42.730682278051972",
              "lng": "-7.333001364022493",
              "ele": "536.1953125"
            },
            {
              "lat": "42.730619413778186",
              "lng": "-7.333183754235506",
              "ele": "524.5364990234375"
            },
            {
              "lat": "42.73035722784698",
              "lng": "-7.333613829687238",
              "ele": "532.0703125"
            },
            {
              "lat": "42.730177519842982",
              "lng": "-7.333834860473871",
              "ele": "535.51171875"
            },
            {
              "lat": "42.729638563469052",
              "lng": "-7.334332158789039",
              "ele": "531.07421875"
            },
            {
              "lat": "42.727410737425089",
              "lng": "-7.335536805912852",
              "ele": "520.03125"
            },
            {
              "lat": "42.726100143045187",
              "lng": "-7.336327973753214",
              "ele": "516.365234375"
            },
            {
              "lat": "42.725928481668234",
              "lng": "-7.336498461663723",
              "ele": "521.84765625"
            },
            {
              "lat": "42.725802669301629",
              "lng": "-7.336929459124804",
              "ele": "522.42578125"
            },
            {
              "lat": "42.725757826119661",
              "lng": "-7.337902011349797",
              "ele": "525.24609375"
            },
            {
              "lat": "42.725596055388451",
              "lng": "-7.33844356611371",
              "ele": "524.7578125"
            },
            {
              "lat": "42.724176747724414",
              "lng": "-7.34095218591392",
              "ele": "516.1328125"
            },
            {
              "lat": "42.724113883450627",
              "lng": "-7.341151172295213",
              "ele": "516.72265625"
            },
            {
              "lat": "42.724185716360807",
              "lng": "-7.341493740677834",
              "ele": "514.92333984375"
            },
            {
              "lat": "42.724949307739735",
              "lng": "-7.342333691194654",
              "ele": "519.7578125"
            },
            {
              "lat": "42.725236807018518",
              "lng": "-7.342543657869101",
              "ele": "517.921875"
            },
            {
              "lat": "42.72556914947927",
              "lng": "-7.342621022835374",
              "ele": "516.37109375"
            },
            {
              "lat": "42.726233918219805",
              "lng": "-7.343118321150541",
              "ele": "515.8846435546875"
            },
            {
              "lat": "42.726862728595734",
              "lng": "-7.34494180418551",
              "ele": "515.8846435546875"
            },
            {
              "lat": "42.727222144603729",
              "lng": "-7.345229303464294",
              "ele": "527.5078125"
            },
            {
              "lat": "42.727958746254444",
              "lng": "-7.346279136836529",
              "ele": "535.591552734375"
            },
            {
              "lat": "42.728425869718194",
              "lng": "-7.346621789038181",
              "ele": "533.921875"
            },
            {
              "lat": "42.729099607095122",
              "lng": "-7.346864864230156",
              "ele": "547.608154296875"
            },
            {
              "lat": "42.729584667831659",
              "lng": "-7.346831755712628",
              "ele": "545.26953125"
            },
            {
              "lat": "42.730186572298408",
              "lng": "-7.346489187330008",
              "ele": "553.625"
            },
            {
              "lat": "42.730617737397552",
              "lng": "-7.346157599240542",
              "ele": "558.9453125"
            },
            {
              "lat": "42.730761487036943",
              "lng": "-7.345892395824194",
              "ele": "560.105224609375"
            },
            {
              "lat": "42.730788392946124",
              "lng": "-7.345483526587486",
              "ele": "564.33984375"
            },
            {
              "lat": "42.730662664398551",
              "lng": "-7.344875670969486",
              "ele": "572.1015625"
            },
            {
              "lat": "42.730671633034945",
              "lng": "-7.344499910250306",
              "ele": "576.87109375"
            },
            {
              "lat": "42.730887215584517",
              "lng": "-7.344334116205573",
              "ele": "575.046875"
            },
            {
              "lat": "42.731192652136087",
              "lng": "-7.344301007688046",
              "ele": "570.9140625"
            },
            {
              "lat": "42.731426171958447",
              "lng": "-7.344389436766505",
              "ele": "571.160400390625"
            },
            {
              "lat": "42.732390761375427",
              "lng": "-7.344993939623237",
              "ele": "567.795654296875"
            },
            {
              "lat": "42.732853358611465",
              "lng": "-7.344588590785861",
              "ele": "550.33203125"
            },
            {
              "lat": "42.733159381896257",
              "lng": "-7.343969419598579",
              "ele": "557.7021484375"
            },
            {
              "lat": "42.733509158715606",
              "lng": "-7.343897838145495",
              "ele": "555.07421875"
            },
            {
              "lat": "42.733765225857496",
              "lng": "-7.343947626650333",
              "ele": "557.21484375"
            },
            {
              "lat": "42.734197145327926",
              "lng": "-7.344084838405252",
              "ele": "566.83447265625"
            },
            {
              "lat": "42.734775831922889",
              "lng": "-7.344560930505395",
              "ele": "562"
            },
            {
              "lat": "42.735489970073104",
              "lng": "-7.34600312076509",
              "ele": "561.61328125"
            },
            {
              "lat": "42.735611256211996",
              "lng": "-7.346168914809823",
              "ele": "561.15234375"
            },
            {
              "lat": "42.735840333625674",
              "lng": "-7.346185510978103",
              "ele": "567.315185546875"
            },
            {
              "lat": "42.736562853679061",
              "lng": "-7.346191043034196",
              "ele": "563.950439453125"
            },
            {
              "lat": "42.736715571954846",
              "lng": "-7.34655573964119",
              "ele": "554.48046875"
            },
            {
              "lat": "42.73679637350142",
              "lng": "-7.347417734563351",
              "ele": "548.12890625"
            },
            {
              "lat": "42.73726349696517",
              "lng": "-7.349042315036058",
              "ele": "540"
            },
            {
              "lat": "42.737361649051309",
              "lng": "-7.350051663815975",
              "ele": "539.9176025390625"
            },
            {
              "lat": "42.736996952444315",
              "lng": "-7.350508058443666",
              "ele": "527.9010009765625"
            },
            {
              "lat": "42.737833298742771",
              "lng": "-7.350167669355869",
              "ele": "517.32666015625"
            },
            {
              "lat": "42.737868502736092",
              "lng": "-7.351351696997881",
              "ele": "515.404052734375"
            },
            {
              "lat": "42.738392120227218",
              "lng": "-7.352171195670962",
              "ele": "512.921875"
            },
            {
              "lat": "42.738847257569432",
              "lng": "-7.353281965479255",
              "ele": "515.8846435546875"
            },
            {
              "lat": "42.73948629386723",
              "lng": "-7.353292945772409",
              "ele": "508.34375"
            },
            {
              "lat": "42.739951657131314",
              "lng": "-7.353439880535007",
              "ele": "515.8846435546875"
            },
            {
              "lat": "42.740089958533645",
              "lng": "-7.35420573502779",
              "ele": "509.875"
            },
            {
              "lat": "42.740052239969373",
              "lng": "-7.355048954486847",
              "ele": "504.4140625"
            },
            {
              "lat": "42.740121390670538",
              "lng": "-7.355265626683831",
              "ele": "508.6746826171875"
            },
            {
              "lat": "42.740305792540312",
              "lng": "-7.35524551011622",
              "ele": "502.75"
            },
            {
              "lat": "42.741145910695195",
              "lng": "-7.355447681620717",
              "ele": "508.6746826171875"
            },
            {
              "lat": "42.741886954754591",
              "lng": "-7.35607766546309",
              "ele": "515.25390625"
            },
            {
              "lat": "42.742601176723838",
              "lng": "-7.356840167194605",
              "ele": "508.6746826171875"
            },
            {
              "lat": "42.743930798023939",
              "lng": "-7.357705347239971",
              "ele": "506.271484375"
            },
            {
              "lat": "42.745309621095657",
              "lng": "-7.357934759929776",
              "ele": "494.796875"
            },
            {
              "lat": "42.746064243838191",
              "lng": "-7.358017656952143",
              "ele": "496.98828125"
            },
            {
              "lat": "42.746980553492904",
              "lng": "-7.358166854828596",
              "ele": "494.60546875"
            },
            {
              "lat": "42.747896779328585",
              "lng": "-7.358647556975484",
              "ele": "499.542236328125"
            },
            {
              "lat": "42.748032733798027",
              "lng": "-7.358268443495035",
              "ele": "489.37890625"
            },
            {
              "lat": "42.748252842575312",
              "lng": "-7.357440646737814",
              "ele": "493.93359375"
            },
            {
              "lat": "42.748347138985991",
              "lng": "-7.357107969000936",
              "ele": "496.99609375"
            },
            {
              "lat": "42.748271701857448",
              "lng": "-7.356442697346211",
              "ele": "498.453125"
            },
            {
              "lat": "42.748555596917868",
              "lng": "-7.355451621115208",
              "ele": "502.90673828125"
            },
            {
              "lat": "42.751786066219211",
              "lng": "-7.356497012078762",
              "ele": "495.2161865234375"
            },
            {
              "lat": "42.751874076202512",
              "lng": "-7.35604832880199",
              "ele": "483.25"
            },
            {
              "lat": "42.751949513331056",
              "lng": "-7.355468133464456",
              "ele": "480.28125"
            },
            {
              "lat": "42.752012377604842",
              "lng": "-7.355305692180991",
              "ele": "480.01171875"
            },
            {
              "lat": "42.752157049253583",
              "lng": "-7.35511994920671",
              "ele": "480"
            },
            {
              "lat": "42.752383444458246",
              "lng": "-7.355034872889519",
              "ele": "480"
            },
            {
              "lat": "42.752421163022518",
              "lng": "-7.354833791032434",
              "ele": "480"
            },
            {
              "lat": "42.752521829679608",
              "lng": "-7.354586189612746",
              "ele": "480.359375"
            },
            {
              "lat": "42.752670859917998",
              "lng": "-7.354502705857158",
              "ele": "492.81298828125"
            },
            {
              "lat": "42.753030611202121",
              "lng": "-7.354269018396735",
              "ele": "482"
            },
            {
              "lat": "42.753124907612801",
              "lng": "-7.354129794985056",
              "ele": "483.0078125"
            },
            {
              "lat": "42.753571411594748",
              "lng": "-7.354098865762353",
              "ele": "484.015625"
            },
            {
              "lat": "42.756136441603303",
              "lng": "-7.353347092866898",
              "ele": "490.890380859375"
            },
            {
              "lat": "42.756539443507791",
              "lng": "-7.35202300362289",
              "ele": "492.81298828125"
            },
            {
              "lat": "42.758183972910047",
              "lng": "-7.352261804044247",
              "ele": "500.984130859375"
            },
            {
              "lat": "42.759606800973415",
              "lng": "-7.353707933798432",
              "ele": "499.0615234375"
            },
            {
              "lat": "42.761207744479179",
              "lng": "-7.353835254907608",
              "ele": "498.5809326171875"
            },
            {
              "lat": "42.762867612764239",
              "lng": "-7.350281411781907",
              "ele": "498.5809326171875"
            },
            {
              "lat": "42.763178665190935",
              "lng": "-7.350134896114469",
              "ele": "488.515625"
            },
            {
              "lat": "42.763851564377546",
              "lng": "-7.350026518106461",
              "ele": "491.33203125"
            },
            {
              "lat": "42.764247693121433",
              "lng": "-7.35003431327641",
              "ele": "491.046875"
            },
            {
              "lat": "42.764675254002213",
              "lng": "-7.350173536688089",
              "ele": "492.0078125"
            },
            {
              "lat": "42.765385871753097",
              "lng": "-7.350088460370898",
              "ele": "490.15625"
            },
            {
              "lat": "42.765480168163776",
              "lng": "-7.349980166181922",
              "ele": "491.6015625"
            },
            {
              "lat": "42.766012335196137",
              "lng": "-7.350131962448359",
              "ele": "497.138916015625"
            },
            {
              "lat": "42.766215344890952",
              "lng": "-7.349709598347545",
              "ele": "491.28125"
            },
            {
              "lat": "42.766485745087266",
              "lng": "-7.349446574226022",
              "ele": "492.828125"
            },
            {
              "lat": "42.766699567437172",
              "lng": "-7.349152620881796",
              "ele": "496.2734375"
            },
            {
              "lat": "42.766932249069214",
              "lng": "-7.348881885409355",
              "ele": "502.0078125"
            },
            {
              "lat": "42.767108269035816",
              "lng": "-7.348758084699512",
              "ele": "502.96875"
            },
            {
              "lat": "42.76728437282145",
              "lng": "-7.348835449665785",
              "ele": "506.7520751953125"
            },
            {
              "lat": "42.767359809949994",
              "lng": "-7.349183550104499",
              "ele": "504.84375"
            },
            {
              "lat": "42.767259227111936",
              "lng": "-7.349756034091115",
              "ele": "510.95703125"
            },
            {
              "lat": "42.767271799966693",
              "lng": "-7.350305300205946",
              "ele": "512.88671875"
            },
            {
              "lat": "42.767416387796402",
              "lng": "-7.350637894123793",
              "ele": "515.87890625"
            },
            {
              "lat": "42.767774127423763",
              "lng": "-7.350932015106082",
              "ele": "524.5364990234375"
            },
            {
              "lat": "42.768057100474834",
              "lng": "-7.350870156660676",
              "ele": "519.69140625"
            },
            {
              "lat": "42.768296068534255",
              "lng": "-7.350808214396238",
              "ele": "521.72265625"
            },
            {
              "lat": "42.768660765141249",
              "lng": "-7.3507618624717",
              "ele": "522.66796875"
            },
            {
              "lat": "42.768918592482805",
              "lng": "-7.350676702335477",
              "ele": "523.28515625"
            },
            {
              "lat": "42.769163763150573",
              "lng": "-7.350854650139809",
              "ele": "521.5625"
            },
            {
              "lat": "42.769289575517178",
              "lng": "-7.351001668721438",
              "ele": "521.78125"
            },
            {
              "lat": "42.769364677369595",
              "lng": "-7.351186154410243",
              "ele": "525.9783935546875"
            },
            {
              "lat": "42.7693712990731",
              "lng": "-7.351844888180494",
              "ele": "519.4375"
            },
            {
              "lat": "42.769415304064751",
              "lng": "-7.351976400241256",
              "ele": "518.79296875"
            },
            {
              "lat": "42.76932729408145",
              "lng": "-7.352579813450575",
              "ele": "512.375"
            },
            {
              "lat": "42.769377585500479",
              "lng": "-7.353183226659894",
              "ele": "509.0703125"
            },
            {
              "lat": "42.769220424816012",
              "lng": "-7.353500397875905",
              "ele": "501.60546875"
            },
            {
              "lat": "42.769270716235042",
              "lng": "-7.353802062571049",
              "ele": "508.6746826171875"
            },
            {
              "lat": "42.769396025687456",
              "lng": "-7.354111354798079",
              "ele": "497.73046875"
            },
            {
              "lat": "42.769704144448042",
              "lng": "-7.354691550135613",
              "ele": "493.296875"
            },
            {
              "lat": "42.769980831071734",
              "lng": "-7.355000926181674",
              "ele": "490.27734375"
            },
            {
              "lat": "42.770100273191929",
              "lng": "-7.355186669155955",
              "ele": "486.0703125"
            },
            {
              "lat": "42.770257517695427",
              "lng": "-7.355217598378658",
              "ele": "486.171875"
            },
            {
              "lat": "42.770458683371544",
              "lng": "-7.355302674695849",
              "ele": "479.3125"
            },
            {
              "lat": "42.770678792148829",
              "lng": "-7.355565698817372",
              "ele": "474.1328125"
            },
            {
              "lat": "42.770898900926113",
              "lng": "-7.355789998546243",
              "ele": "478.19140625"
            },
            {
              "lat": "42.770999483764172",
              "lng": "-7.356029888615012",
              "ele": "479.8515625"
            },
            {
              "lat": "42.771313888952136",
              "lng": "-7.356192329898477",
              "ele": "479.64453125"
            },
            {
              "lat": "42.771458560600877",
              "lng": "-7.356401206925511",
              "ele": "477.78515625"
            },
            {
              "lat": "42.771533997729421",
              "lng": "-7.356888530775905",
              "ele": "475.13671875"
            },
            {
              "lat": "42.771703731268644",
              "lng": "-7.357894275337458",
              "ele": "483.680419921875"
            },
            {
              "lat": "42.771923337131739",
              "lng": "-7.358064260333777",
              "ele": "477.2265625"
            },
            {
              "lat": "42.772237742319703",
              "lng": "-7.358358213678002",
              "ele": "480.19140625"
            },
            {
              "lat": "42.772332038730383",
              "lng": "-7.358543872833252",
              "ele": "480.0390625"
            },
            {
              "lat": "42.772382330149412",
              "lng": "-7.358582513406873",
              "ele": "480.55859375"
            },
            {
              "lat": "42.772932937368751",
              "lng": "-7.360826013609767",
              "ele": "503.8681640625"
            },
            {
              "lat": "42.773193446919322",
              "lng": "-7.361522214487195",
              "ele": "491.88671875"
            },
            {
              "lat": "42.773238457739353",
              "lng": "-7.361654648557305",
              "ele": "498.4921875"
            },
            {
              "lat": "42.773606758564711",
              "lng": "-7.361676776781678",
              "ele": "499.8515625"
            },
            {
              "lat": "42.7736521884799",
              "lng": "-7.361803594976664",
              "ele": "504.8294677734375"
            },
            {
              "lat": "42.773597957566381",
              "lng": "-7.362372977659106",
              "ele": "496.84375"
            },
            {
              "lat": "42.773400312289596",
              "lng": "-7.362870359793305",
              "ele": "494.91015625"
            },
            {
              "lat": "42.773229656741023",
              "lng": "-7.363566560670734",
              "ele": "490.5625"
            },
            {
              "lat": "42.773193698376417",
              "lng": "-7.364715887233615",
              "ele": "493.17578125"
            },
            {
              "lat": "42.77329252101481",
              "lng": "-7.365257441997528",
              "ele": "492.54296875"
            },
            {
              "lat": "42.773346416652203",
              "lng": "-7.365644266828895",
              "ele": "490.1796875"
            },
            {
              "lat": "42.77317576110363",
              "lng": "-7.36663886345923",
              "ele": "483.76171875"
            },
            {
              "lat": "42.773202667012811",
              "lng": "-7.367755081504583",
              "ele": "485.14453125"
            },
            {
              "lat": "42.773166708648205",
              "lng": "-7.368351789191365",
              "ele": "485.171875"
            },
            {
              "lat": "42.773211551830173",
              "lng": "-7.368959644809365",
              "ele": "480.81640625"
            },
            {
              "lat": "42.773202667012811",
              "lng": "-7.369998497888446",
              "ele": "493.2935791015625"
            },
            {
              "lat": "42.773269973695278",
              "lng": "-7.370863845571876",
              "ele": "483.68359375"
            },
            {
              "lat": "42.773320348933339",
              "lng": "-7.371382182464004",
              "ele": "485.65625"
            },
            {
              "lat": "42.773454040288925",
              "lng": "-7.372186677530408",
              "ele": "486.53125"
            },
            {
              "lat": "42.77357985265553",
              "lng": "-7.372871898114681",
              "ele": "487.234375"
            },
            {
              "lat": "42.773516569286585",
              "lng": "-7.373640770092607",
              "ele": "485.25390625"
            },
            {
              "lat": "42.773478850722313",
              "lng": "-7.374244183301926",
              "ele": "485.71484375"
            },
            {
              "lat": "42.773881265893579",
              "lng": "-7.375636668875814",
              "ele": "489.4483642578125"
            },
            {
              "lat": "42.774215787649155",
              "lng": "-7.378023583441973",
              "ele": "491.3709716796875"
            },
            {
              "lat": "42.775740707293153",
              "lng": "-7.382960608229041",
              "ele": "464.934814453125"
            },
            {
              "lat": "42.776677804067731",
              "lng": "-7.384442947804928",
              "ele": "461.5701904296875"
            },
            {
              "lat": "42.776370774954557",
              "lng": "-7.385661005973816",
              "ele": "447.55859375"
            },
            {
              "lat": "42.776262983679771",
              "lng": "-7.387451380491257",
              "ele": "449.625"
            },
            {
              "lat": "42.776135914027691",
              "lng": "-7.388975294306874",
              "ele": "459.6475830078125"
            },
            {
              "lat": "42.776370774954557",
              "lng": "-7.392954854294658",
              "ele": "442.3438720703125"
            },
            {
              "lat": "42.776137255132198",
              "lng": "-7.396159758791328",
              "ele": "430"
            },
            {
              "lat": "42.776191150769591",
              "lng": "-7.397950133308768",
              "ele": "428.78515625"
            },
            {
              "lat": "42.775562340393662",
              "lng": "-7.400293042883277",
              "ele": "431.28857421875"
            },
            {
              "lat": "42.775770546868443",
              "lng": "-7.402609214186668",
              "ele": "426.9627685546875"
            },
            {
              "lat": "42.77555488049984",
              "lng": "-7.404068000614643",
              "ele": "429.365966796875"
            },
            {
              "lat": "42.775851599872112",
              "lng": "-7.405438357964158",
              "ele": "423.5980224609375"
            },
            {
              "lat": "42.775851599872112",
              "lng": "-7.405858375132084",
              "ele": "421.703125"
            },
            {
              "lat": "42.775579439476132",
              "lng": "-7.407167796045542",
              "ele": "421"
            },
            {
              "lat": "42.775340471416712",
              "lng": "-7.407314730808139",
              "ele": "421"
            },
            {
              "lat": "42.77515179477632",
              "lng": "-7.407461749389768",
              "ele": "421"
            },
            {
              "lat": "42.774956915527582",
              "lng": "-7.407825356349349",
              "ele": "421"
            },
            {
              "lat": "42.774881394580007",
              "lng": "-7.408488616347313",
              "ele": "421.92578125"
            },
            {
              "lat": "42.774975774809718",
              "lng": "-7.408753652125597",
              "ele": "424.5594482421875"
            },
            {
              "lat": "42.775063784793019",
              "lng": "-7.408838728442788",
              "ele": "422"
            },
            {
              "lat": "42.775384476408362",
              "lng": "-7.409055400639772",
              "ele": "421.7890625"
            },
            {
              "lat": "42.775497632101178",
              "lng": "-7.409210046753287",
              "ele": "421.6328125"
            },
            {
              "lat": "42.775805750861764",
              "lng": "-7.411484476178885",
              "ele": "423.6015625"
            },
            {
              "lat": "42.775911949574947",
              "lng": "-7.41181262768805",
              "ele": "427.443359375"
            },
            {
              "lat": "42.776327608153224",
              "lng": "-7.412706641480327",
              "ele": "427.22265625"
            },
            {
              "lat": "42.776786601170897",
              "lng": "-7.412613853812218",
              "ele": "429.51171875"
            },
            {
              "lat": "42.776830606162548",
              "lng": "-7.412815019488335",
              "ele": "430.3272705078125"
            },
            {
              "lat": "42.777157668024302",
              "lng": "-7.413665950298309",
              "ele": "445.6171875"
            },
            {
              "lat": "42.777214245870709",
              "lng": "-7.414044979959726",
              "ele": "450.30859375"
            }
          ]
        }